ncs/__init__.py
ncs/client.py
ncs/parser.py
ncs/song.py
ncspy-0.2.4.dist-info/LICENSE
ncspy-0.2.4.dist-info/METADATA
ncspy-0.2.4.dist-info/WHEEL
ncspy-0.2.4.dist-info/top_level.txt
ncspy-0.2.4.dist-info/RECORD
