Metadata-Version: 2.1
Name: ncspy
Version: 0.2.4
Summary: A NoCopyrightSounds "API" wrapper written with asyncio.
Home-page: https://github.com/Vincydotzsh/pyncs
Author: Vincy.zsh
Author-email: Vincysuper07@gmail.com
License: UNKNOWN
Platform: UNKNOWN
Classifier: Programming Language :: Python :: 3
Classifier: Operating System :: OS Independent
Requires-Python: >=3.7
License-File: LICENSE
Requires-Dist: aiohttp
Requires-Dist: beautifulsoup4
Requires-Dist: slimit
